log4data/__init__.py
log4data/monitoring.py
log4data/utils.py
log4data-0.1.3.dist-info/licenses/LICENSE
log4data-0.1.3.dist-info/METADATA
log4data-0.1.3.dist-info/WHEEL
log4data-0.1.3.dist-info/top_level.txt
log4data-0.1.3.dist-info/RECORD
