Metadata-Version: 2.4
Name: log4data
Version: 0.1.3
Summary: Helper library to configure logging for python
Author-email: Jordi Puig Rabat <jordipuig37@gmail.com>
Project-URL: Homepage, https://github.com/jordipuig37/logging-4-data
Project-URL: Issues, https://github.com/jordipuig37/logging-4-data/issues
Classifier: Programming Language :: Python :: 3
Classifier: License :: OSI Approved :: MIT License
Classifier: Operating System :: OS Independent
Requires-Python: >=3.8
License-File: LICENSE
Dynamic: license-file
